n0s1/__init__.py
n0s1/local_run.py
n0s1/n0s1.py
n0s1/scanner.py
n0s1/test_sdk.py
n0s1/clients/__init__.py
n0s1/clients/http_client.py
n0s1/clients/linear_graphql_client.py
n0s1/common/__init__.py
n0s1/common/utils.py
n0s1/config/config.yaml
n0s1/config/config01.yaml
n0s1/config/gitleaks.yaml
n0s1/config/regex.toml
n0s1/config/regex.yaml
n0s1/controllers/__init__.py
n0s1/controllers/asana_controller.py
n0s1/controllers/confluence_controller.py
n0s1/controllers/github_controller.py
n0s1/controllers/gitlab_controller.py
n0s1/controllers/hollow_controller.py
n0s1/controllers/jira_controller.py
n0s1/controllers/linear_controller.py
n0s1/controllers/local_filesystem_controller.py
n0s1/controllers/platform_controller.py
n0s1/controllers/slack_controller.py
n0s1/controllers/spark1.py
n0s1/controllers/test01.py
n0s1/controllers/test1.py
n0s1/controllers/wrike_controller.py
n0s1/controllers/zendesk_controller.py
n0s1/reporting/__init__.py
n0s1/reporting/report_gitlab.py
n0s1/reporting/report_gitlab_OK.py
n0s1/reporting/report_gitlab_sast.py
n0s1/reporting/report_sarif.py
n0s1-1.1.0.dist-info/licenses/LICENSE
n0s1-1.1.0.dist-info/METADATA
n0s1-1.1.0.dist-info/WHEEL
n0s1-1.1.0.dist-info/entry_points.txt
n0s1-1.1.0.dist-info/top_level.txt
n0s1-1.1.0.dist-info/RECORD
