Metadata-Version: 2.4
Name: n0s1
Version: 1.1.0
Summary: Secret Scanner for Slack, Jira, Confluence, Asana, Wrike, Linear, Zendesk, GitHub and GitLab. Prevent credential leaks with n0s1.
Home-page: https://spark1.us/n0s1
Author: Spark 1
Author-email: contact@spark1.us
Project-URL: Bug Reports, https://github.com/spark1security/n0s1/issues
Project-URL: Funding, https://gofund.me/c6a0520c
Project-URL: Source, https://github.com/spark1security/n0s1
Keywords: security,cybersecurity,scanner,secret scanner,secret leak,data leak,Slack,Jira,Confluence,Asana,Wrike,Linear,Zendesk,GitHub,GitLab,security scanner,data loss prevention
Classifier: Development Status :: 3 - Alpha
Classifier: Intended Audience :: Developers
Classifier: Intended Audience :: Information Technology
Classifier: Operating System :: OS Independent
Classifier: Topic :: Security
Classifier: Topic :: Software Development
Classifier: Topic :: System :: Monitoring
Classifier: Topic :: Utilities
Classifier: License :: OSI Approved :: GNU General Public License v3 or later (GPLv3+)
Classifier: Programming Language :: Python :: 3.9
Classifier: Programming Language :: Python :: 3.10
Classifier: Programming Language :: Python :: 3.11
Classifier: Programming Language :: Python :: 3.12
Classifier: Programming Language :: Python :: 3.13
Requires-Python: >=3.9, <4
License-File: LICENSE
Requires-Dist: requests
Requires-Dist: toml
Requires-Dist: jira
Requires-Dist: pyyaml
Requires-Dist: atlassian-python-api
Requires-Dist: asana==3.2.2
Requires-Dist: zenpy
Requires-Dist: PyGithub
Requires-Dist: python-gitlab
Requires-Dist: WrikePy
Requires-Dist: BeautifulSoup4
Requires-Dist: slack_sdk
Requires-Dist: langchain-text-splitters
Provides-Extra: dev
Requires-Dist: check-manifest; extra == "dev"
Provides-Extra: test
Requires-Dist: coverage; extra == "test"
Dynamic: author
Dynamic: author-email
Dynamic: classifier
Dynamic: description
Dynamic: description-content-type
Dynamic: home-page
Dynamic: keywords
Dynamic: license-file
Dynamic: project-url
Dynamic: provides-extra
Dynamic: requires-dist
Dynamic: requires-python
Dynamic: summary
